<svs:ValueSet xmlns:svs="urn:ihe:iti:svs:2008" id="1.2.3.4.5.7.8.9.72827295808269.82101103" version="20150624" displayName="DATIM disaggregator for Reg on HRH_PRE">
  <svs:ConceptList xml:lang="en-US">
    <svs:Concept code="Doctors" displayName="Doctors" codeSystem="urn:www.datim.org:disaggregators:HRH_PRE:Reg"/>
    <svs:Concept code="Lab Professionals" displayName="Lab Professionals" codeSystem="urn:www.datim.org:disaggregators:HRH_PRE:Reg"/>
    <svs:Concept code="Midwives" displayName="Midwives" codeSystem="urn:www.datim.org:disaggregators:HRH_PRE:Reg"/>
    <svs:Concept code="Nurses" displayName="Nurses" codeSystem="urn:www.datim.org:disaggregators:HRH_PRE:Reg"/>
    <svs:Concept code="Other Cadre" displayName="Other Cadre" codeSystem="urn:www.datim.org:disaggregators:HRH_PRE:Reg"/>
    <svs:Concept code="Social Service Workers" displayName="Social Service Workers" codeSystem="urn:www.datim.org:disaggregators:HRH_PRE:Reg"/>
  </svs:ConceptList>
</svs:ValueSet>